ofxdb/__init__.py
ofxdb/cfg.py
ofxdb-0.0.2.dist-info/LICENSE
ofxdb-0.0.2.dist-info/METADATA
ofxdb-0.0.2.dist-info/WHEEL
ofxdb-0.0.2.dist-info/top_level.txt
ofxdb-0.0.2.dist-info/RECORD
