Metadata-Version: 2.1
Name: ofxdb
Version: 0.0.2
Summary: DB Generator for OFX Financial Statement Data
Home-page: https://github.com/finarrow/ofxdb
Author: Ricardo Rosales
Author-email: rrosales1028@gmail.com
License: UNKNOWN
Platform: UNKNOWN
Classifier: Development Status :: 1 - Planning
Classifier: Environment :: Console
Classifier: Programming Language :: Python
Classifier: Programming Language :: Python :: 3
Classifier: Programming Language :: Python :: 3.7
Classifier: Programming Language :: Python :: 3.8
Classifier: License :: OSI Approved :: MIT License
Classifier: Operating System :: OS Independent
Classifier: Intended Audience :: Developers
Classifier: Topic :: Office/Business :: Financial :: Investment
Requires-Python: >=3.7
Requires-Dist: ofxtools (>=0.8.20)
Requires-Dist: pandas (>=1.0.1)
Requires-Dist: keyring (>=21.1.0)
